<?xml version="1.0" encoding="utf-8"?>
<odoo>

    <template id="portal_my_product" name="My Portal">
        <t t-call="portal.portal_layout">
            <t t-set="my_details" t-value="True"/>
            <div class="o_portal_my_home">
                <div class="oe_structure" id="oe_structure_portal_my_home_1"/>
                <h3>Product List</h3>
                <div class="o_portal_docs list-group">
                </div>
            </div>
            <div class="oe_structure" id="oe_structure_portal_my_home_2"/>
        </t>
    </template>
    

</odoo>
